{
  "updated": "2025-08-09T14:42:08.500Z",
  "entries": [
    {
      "ticker": "SBET",
      "user": {
        "id": "935743401540857866",
        "name": "Cubby"
      },
      "messageId": "1399309827208908860",
      "channelId": "1397977551078686871",
      "guildId": "1397974486581772494",
      "link": "https://discord.com/channels/1397974486581772494/1397977551078686871/1399309827208908860",
      "timestamp": "2025-07-28T08:37:40.726Z",
      "content": "$SBET\nלקראת החלטה - עולה או יורדת,\nMACD חיובי \nRSI בול בחצי\nווליום מוכרים יורד\nלא לשכוח זו חברה שקונה אית'ריום ומדללת ומדללת ומדללת"
    },
    {
      "ticker": "RSI",
      "user": {
        "id": "935743401540857866",
        "name": "Cubby"
      },
      "messageId": "1399309827208908860",
      "channelId": "1397977551078686871",
      "guildId": "1397974486581772494",
      "link": "https://discord.com/channels/1397974486581772494/1397977551078686871/1399309827208908860",
      "timestamp": "2025-07-28T08:37:40.726Z",
      "content": "$SBET\nלקראת החלטה - עולה או יורדת,\nMACD חיובי \nRSI בול בחצי\nווליום מוכרים יורד\nלא לשכוח זו חברה שקונה אית'ריום ומדללת ומדללת ומדללת"
    }
  ],
  "checkpoints": {
    "1397977551078686871": {
      "lastProcessedId": "1399295594505441384",
      "lastProcessedAt": "2025-07-28T07:41:07.385Z"
    }
  }
}